image_trasnformations/__init__.py
image_trasnformations/hello.py
image_transformations-0.0.1.dist-info/LICENSE
image_transformations-0.0.1.dist-info/METADATA
image_transformations-0.0.1.dist-info/WHEEL
image_transformations-0.0.1.dist-info/top_level.txt
image_transformations-0.0.1.dist-info/RECORD
