Metadata-Version: 2.1
Name: image-transformations
Version: 0.0.1
Summary: A basic image transformations using numpy and opencv
Home-page: UNKNOWN
Author: Mauricio-xxi (Alvaro Camacho)
Author-email: <alvarocamachodavila@gmail.com>
License: UNKNOWN
Keywords: python,image,numpy,RGB,Vectorize,opencv
Platform: UNKNOWN
Classifier: Development Status :: 1 - Planning
Classifier: Intended Audience :: Developers
Classifier: Programming Language :: Python :: 3
Classifier: Operating System :: Unix
Classifier: Operating System :: MacOS :: MacOS X
Classifier: Operating System :: Microsoft :: Windows
Requires-Dist: numpy
Requires-Dist: opencv-python
